Proxer/__init__.py
Proxer-1.3.5.dist-info/METADATA
Proxer-1.3.5.dist-info/WHEEL
Proxer-1.3.5.dist-info/top_level.txt
Proxer-1.3.5.dist-info/RECORD
